<?xml version="1.0" encoding="utf-8" ?><dwsync><file name=".DS_Store" server="michelleyoder.com" local="3471842075" remote="12061783472" /><file name="DSC_1914-.jpg" server="michelleyoder.com" local="3471842098" remote="12061783472" /><file name="DSC_3415-.jpg" server="michelleyoder.com" local="3471842099" remote="12061783472" /><file name="DSC_3809.jpg" server="michelleyoder.com" local="3471842102" remote="12061783472" /><file name="DSC_4947-.jpg" server="michelleyoder.com" local="3471842100" remote="12061783472" /><file name="DSC_5305-.jpg" server="michelleyoder.com" local="3471842103" remote="12061783472" /><file name="DSC_5922-.jpg" server="michelleyoder.com" local="3471842101" remote="12061783472" /><file name="DSC_8510-.jpg" server="michelleyoder.com" local="3471842102" remote="12061783472" /><file name="DSC_8885.jpg" server="michelleyoder.com" local="3471842100" remote="12061783532" /><file name="DSC_9042-.jpg" server="michelleyoder.com" local="3471842103" remote="12061783532" /><file name="DSC_9471-.jpg" server="michelleyoder.com" local="3471842104" remote="12061783532" /><file name="mm_01.jpg" server="michelleyoder.com" local="3471842095" remote="12061783532" /><file name="mm_03.jpg" server="michelleyoder.com" local="3471842096" remote="12061783532" /><file name="mm_06.jpg" server="michelleyoder.com" local="3471842097" remote="12061783532" /><file name="mm_12.jpg" server="michelleyoder.com" local="3471842097" remote="12061783532" /><file name="mm_14.jpg" server="michelleyoder.com" local="3471842098" remote="12061783532" /></dwsync>